{"id":"/YBX","dependencies":[{"name":"D:\\cloudsystems-dev-tasks\\fortydays\\node_modules\\@material-ui\\core\\package.json","includedInParent":true,"mtime":1533715641046},{"name":"D:\\cloudsystems-dev-tasks\\fortydays\\package.json","includedInParent":true,"mtime":1533725059168},{"name":"@babel/runtime/helpers/builtin/interopRequireDefault","loc":{"line":3,"column":37},"parent":"D:\\cloudsystems-dev-tasks\\fortydays\\node_modules\\@material-ui\\core\\Modal\\index.js","resolved":"D:\\cloudsystems-dev-tasks\\fortydays\\node_modules\\@babel\\runtime\\helpers\\builtin\\interopRequireDefault.js"},{"name":"./Modal","loc":{"line":21,"column":44},"parent":"D:\\cloudsystems-dev-tasks\\fortydays\\node_modules\\@material-ui\\core\\Modal\\index.js","resolved":"D:\\cloudsystems-dev-tasks\\fortydays\\node_modules\\@material-ui\\core\\Modal\\Modal.js"},{"name":"./ModalManager","loc":{"line":23,"column":51},"parent":"D:\\cloudsystems-dev-tasks\\fortydays\\node_modules\\@material-ui\\core\\Modal\\index.js","resolved":"D:\\cloudsystems-dev-tasks\\fortydays\\node_modules\\@material-ui\\core\\Modal\\ModalManager.js"}],"generated":{"js":"\"use strict\";var e=require(\"@babel/runtime/helpers/builtin/interopRequireDefault\");Object.defineProperty(exports,\"__esModule\",{value:!0}),Object.defineProperty(exports,\"default\",{enumerable:!0,get:function(){return r.default}}),Object.defineProperty(exports,\"ModalManager\",{enumerable:!0,get:function(){return t.default}});var r=e(require(\"./Modal\")),t=e(require(\"./ModalManager\"));","map":{"mappings":[{"source":"..\\node_modules\\@material-ui\\core\\Modal\\index.js","original":{"line":1,"column":0},"generated":{"line":1,"column":0}},{"source":"..\\node_modules\\@material-ui\\core\\Modal\\index.js","original":{"line":3,"column":0},"generated":{"line":1,"column":13}},{"source":"..\\node_modules\\@material-ui\\core\\Modal\\index.js","name":"_interopRequireDefault","original":{"line":3,"column":4},"generated":{"line":1,"column":17}},{"source":"..\\node_modules\\@material-ui\\core\\Modal\\index.js","name":"require","original":{"line":3,"column":29},"generated":{"line":1,"column":19}},{"source":"..\\node_modules\\@material-ui\\core\\Modal\\index.js","original":{"line":3,"column":37},"generated":{"line":1,"column":27}},{"source":"..\\node_modules\\@material-ui\\core\\Modal\\index.js","name":"Object","original":{"line":5,"column":0},"generated":{"line":1,"column":83}},{"source":"..\\node_modules\\@material-ui\\core\\Modal\\index.js","name":"defineProperty","original":{"line":5,"column":7},"generated":{"line":1,"column":90}},{"source":"..\\node_modules\\@material-ui\\core\\Modal\\index.js","name":"exports","original":{"line":5,"column":22},"generated":{"line":1,"column":105}},{"source":"..\\node_modules\\@material-ui\\core\\Modal\\index.js","original":{"line":5,"column":31},"generated":{"line":1,"column":113}},{"source":"..\\node_modules\\@material-ui\\core\\Modal\\index.js","original":{"line":5,"column":45},"generated":{"line":1,"column":126}},{"source":"..\\node_modules\\@material-ui\\core\\Modal\\index.js","original":{"line":6,"column":9},"generated":{"line":1,"column":127}},{"source":"..\\node_modules\\@material-ui\\core\\Modal\\index.js","original":{"line":6,"column":9},"generated":{"line":1,"column":134}},{"source":"..\\node_modules\\@material-ui\\core\\Modal\\index.js","name":"Object","original":{"line":8,"column":0},"generated":{"line":1,"column":138}},{"source":"..\\node_modules\\@material-ui\\core\\Modal\\index.js","name":"defineProperty","original":{"line":8,"column":7},"generated":{"line":1,"column":145}},{"source":"..\\node_modules\\@material-ui\\core\\Modal\\index.js","name":"exports","original":{"line":8,"column":22},"generated":{"line":1,"column":160}},{"source":"..\\node_modules\\@material-ui\\core\\Modal\\index.js","original":{"line":8,"column":31},"generated":{"line":1,"column":168}},{"source":"..\\node_modules\\@material-ui\\core\\Modal\\index.js","original":{"line":8,"column":42},"generated":{"line":1,"column":178}},{"source":"..\\node_modules\\@material-ui\\core\\Modal\\index.js","original":{"line":9,"column":14},"generated":{"line":1,"column":179}},{"source":"..\\node_modules\\@material-ui\\core\\Modal\\index.js","original":{"line":9,"column":14},"generated":{"line":1,"column":191}},{"source":"..\\node_modules\\@material-ui\\core\\Modal\\index.js","original":{"line":10,"column":7},"generated":{"line":1,"column":193}},{"source":"..\\node_modules\\@material-ui\\core\\Modal\\index.js","original":{"line":10,"column":7},"generated":{"line":1,"column":197}},{"source":"..\\node_modules\\@material-ui\\core\\Modal\\index.js","name":"_Modal","original":{"line":11,"column":11},"generated":{"line":1,"column":208}},{"source":"..\\node_modules\\@material-ui\\core\\Modal\\index.js","name":"_Modal","original":{"line":11,"column":11},"generated":{"line":1,"column":215}},{"source":"..\\node_modules\\@material-ui\\core\\Modal\\index.js","name":"default","original":{"line":11,"column":18},"generated":{"line":1,"column":217}},{"source":"..\\node_modules\\@material-ui\\core\\Modal\\index.js","name":"Object","original":{"line":14,"column":0},"generated":{"line":1,"column":228}},{"source":"..\\node_modules\\@material-ui\\core\\Modal\\index.js","name":"defineProperty","original":{"line":14,"column":7},"generated":{"line":1,"column":235}},{"source":"..\\node_modules\\@material-ui\\core\\Modal\\index.js","name":"exports","original":{"line":14,"column":22},"generated":{"line":1,"column":250}},{"source":"..\\node_modules\\@material-ui\\core\\Modal\\index.js","original":{"line":14,"column":31},"generated":{"line":1,"column":258}},{"source":"..\\node_modules\\@material-ui\\core\\Modal\\index.js","original":{"line":14,"column":47},"generated":{"line":1,"column":273}},{"source":"..\\node_modules\\@material-ui\\core\\Modal\\index.js","original":{"line":15,"column":14},"generated":{"line":1,"column":274}},{"source":"..\\node_modules\\@material-ui\\core\\Modal\\index.js","original":{"line":15,"column":14},"generated":{"line":1,"column":286}},{"source":"..\\node_modules\\@material-ui\\core\\Modal\\index.js","original":{"line":16,"column":7},"generated":{"line":1,"column":288}},{"source":"..\\node_modules\\@material-ui\\core\\Modal\\index.js","original":{"line":16,"column":7},"generated":{"line":1,"column":292}},{"source":"..\\node_modules\\@material-ui\\core\\Modal\\index.js","name":"_ModalManager","original":{"line":17,"column":11},"generated":{"line":1,"column":303}},{"source":"..\\node_modules\\@material-ui\\core\\Modal\\index.js","name":"_ModalManager","original":{"line":17,"column":11},"generated":{"line":1,"column":310}},{"source":"..\\node_modules\\@material-ui\\core\\Modal\\index.js","name":"default","original":{"line":17,"column":25},"generated":{"line":1,"column":312}},{"source":"..\\node_modules\\@material-ui\\core\\Modal\\index.js","original":{"line":21,"column":0},"generated":{"line":1,"column":323}},{"source":"..\\node_modules\\@material-ui\\core\\Modal\\index.js","name":"_Modal","original":{"line":21,"column":4},"generated":{"line":1,"column":327}},{"source":"..\\node_modules\\@material-ui\\core\\Modal\\index.js","name":"_interopRequireDefault","original":{"line":21,"column":13},"generated":{"line":1,"column":329}},{"source":"..\\node_modules\\@material-ui\\core\\Modal\\index.js","name":"require","original":{"line":21,"column":36},"generated":{"line":1,"column":331}},{"source":"..\\node_modules\\@material-ui\\core\\Modal\\index.js","original":{"line":21,"column":44},"generated":{"line":1,"column":339}},{"source":"..\\node_modules\\@material-ui\\core\\Modal\\index.js","name":"_ModalManager","original":{"line":23,"column":4},"generated":{"line":1,"column":351}},{"source":"..\\node_modules\\@material-ui\\core\\Modal\\index.js","name":"_interopRequireDefault","original":{"line":23,"column":20},"generated":{"line":1,"column":353}},{"source":"..\\node_modules\\@material-ui\\core\\Modal\\index.js","name":"require","original":{"line":23,"column":43},"generated":{"line":1,"column":355}},{"source":"..\\node_modules\\@material-ui\\core\\Modal\\index.js","original":{"line":23,"column":51},"generated":{"line":1,"column":363}}],"sources":{"..\\node_modules\\@material-ui\\core\\Modal\\index.js":"\"use strict\";\n\nvar _interopRequireDefault = require(\"@babel/runtime/helpers/builtin/interopRequireDefault\");\n\nObject.defineProperty(exports, \"__esModule\", {\n  value: true\n});\nObject.defineProperty(exports, \"default\", {\n  enumerable: true,\n  get: function get() {\n    return _Modal.default;\n  }\n});\nObject.defineProperty(exports, \"ModalManager\", {\n  enumerable: true,\n  get: function get() {\n    return _ModalManager.default;\n  }\n});\n\nvar _Modal = _interopRequireDefault(require(\"./Modal\"));\n\nvar _ModalManager = _interopRequireDefault(require(\"./ModalManager\"));"},"lineCount":null}},"hash":"a56c26fb819446c1534f24190ad89622","cacheData":{"env":{}}}